cv2_dnn_model_files/__init__.py
cv2_dnn_model_files/deploy.prototxt.txt
cv2_dnn_model_files/res10_300x300_ssd_iter_140000.caffemodel
emotion_detection/__init__.py
emotion_detection/evaluate.py
emotion_detection/fer_data_utils.py
emotion_detection/train.py
multitask_rag/__init__.py
multitask_rag/evaluate.py
multitask_rag/train.py
multitask_rag/utk_data_utils.py
vision_utils/__init__.py
vision_utils/custom_architectures.py
vision_utils/custom_torch_utils.py
vision_utils/cv2_deploy.py
vision_utils/face_utils.py
vision_utils/process_fer_images.py
democlassi-0.5.1.dist-info/LICENSE
democlassi-0.5.1.dist-info/METADATA
democlassi-0.5.1.dist-info/WHEEL
democlassi-0.5.1.dist-info/top_level.txt
democlassi-0.5.1.dist-info/RECORD
