Metadata-Version: 2.1
Name: democlassi
Version: 0.5.1
Summary: Collection of my python functions for training pytorch models to classify emotion, age, race, gender
Home-page: https://github.com/AlkaSaliss/DEmoClassi
Author: A. Alka M. Salissou
Author-email: alkasalissou@hotmail.com
License: LICENSE
Platform: UNKNOWN
Classifier: Programming Language :: Python :: 3.6
Classifier: License :: OSI Approved :: MIT License
Classifier: Operating System :: OS Independent
Requires-Dist: torch (==1.8.1)
Requires-Dist: torchvision (==0.9.1)
Requires-Dist: pytorch-ignite (==0.3.0)
Requires-Dist: imutils (==0.5.4)
Requires-Dist: dlib (==19.22.0)
Requires-Dist: kaggle
Requires-Dist: tensorboard
Requires-Dist: tensorboardX
Requires-Dist: tqdm
Requires-Dist: pillow (==8.2.0)
Requires-Dist: matplotlib
Requires-Dist: scikit-learn (==0.24.2)
Requires-Dist: scikit-image (==0.18.1)
Requires-Dist: opencv-python
Requires-Dist: pandas
